{
  "node": {
    "00e36b79e9e9845030d5c7475a1b5177c7dc003070": {
      "workers": {
        "app/admin/login/page": {
          "moduleId": 38959,
          "async": false,
          "exportedName": "adminLogout",
          "filename": "gestao-e-salao/src/app/actions/admin.ts"
        }
      },
      "exportedName": "adminLogout",
      "filename": "gestao-e-salao/src/app/actions/admin.ts"
    },
    "40265a3fdd3edee68697e402a68fbb07fc46362565": {
      "workers": {
        "app/admin/login/page": {
          "moduleId": 38959,
          "async": false,
          "exportedName": "adminLogin",
          "filename": "gestao-e-salao/src/app/actions/admin.ts"
        }
      },
      "exportedName": "adminLogin",
      "filename": "gestao-e-salao/src/app/actions/admin.ts"
    }
  },
  "edge": {}
}